{
	"configurations" : 
	[
		{
			"directories" : 
			[
				{
					"build" : ".",
					"minimumCMakeVersion" : 
					{
						"string" : "3.20"
					},
					"projectIndex" : 0,
					"source" : ".",
					"targetIndexes" : 
					[
						0
					]
				}
			],
			"name" : "Debug",
			"projects" : 
			[
				{
					"directoryIndexes" : 
					[
						0
					],
					"name" : "LAB_2_Supermarket_Modeling",
					"targetIndexes" : 
					[
						0
					]
				}
			],
			"targets" : 
			[
				{
					"directoryIndex" : 0,
					"id" : "LAB_2_Supermarket_Modeling::@6890427a1f51a3e7e1df",
					"jsonFile" : "target-LAB_2_Supermarket_Modeling-Debug-198a94adc74b2fcd64ef.json",
					"name" : "LAB_2_Supermarket_Modeling",
					"projectIndex" : 0
				}
			]
		}
	],
	"kind" : "codemodel",
	"paths" : 
	{
		"build" : "/cygdrive/c/C++/LAB_2_Supermarket_Modeling/cmake-build-debug",
		"source" : "/cygdrive/c/C++/LAB_2_Supermarket_Modeling"
	},
	"version" : 
	{
		"major" : 2,
		"minor" : 2
	}
}
